MANIFEST.in
setup.cfg
setup.py
garlicsim_wx/__init__.py
garlicsim_wx/gui_project.py
garlicsim_wx/lgpl2.1_license.txt
garlicsim_wx.egg-info/PKG-INFO
garlicsim_wx.egg-info/SOURCES.txt
garlicsim_wx.egg-info/dependency_links.txt
garlicsim_wx.egg-info/not-zip-safe
garlicsim_wx.egg-info/requires.txt
garlicsim_wx.egg-info/top_level.txt
garlicsim_wx/app/__init__.py
garlicsim_wx/app/app.py
garlicsim_wx/bootstrap/__init__.py
garlicsim_wx/bootstrap/bootstrap.py
garlicsim_wx/bootstrap/bootstrap_wx.py
garlicsim_wx/frame/__init__.py
garlicsim_wx/frame/frame.py
garlicsim_wx/frame/images/__init__.py
garlicsim_wx/frame/images/check.png
garlicsim_wx/frame/images/new.png
garlicsim_wx/frame/images/open.png
garlicsim_wx/frame/images/save.png
garlicsim_wx/general_misc/__init__.py
garlicsim_wx/general_misc/color_tools.py
garlicsim_wx/general_misc/cute_base_timer.py
garlicsim_wx/general_misc/cute_menu.py
garlicsim_wx/general_misc/cute_timer.py
garlicsim_wx/general_misc/emitting_ordered_set.py
garlicsim_wx/general_misc/emitting_weak_key_default_dict.py
garlicsim_wx/general_misc/flag_raiser.py
garlicsim_wx/general_misc/get_lines.py
garlicsim_wx/general_misc/misc_tools.py
garlicsim_wx/general_misc/stringsaver.py
garlicsim_wx/general_misc/thread_timer.py
garlicsim_wx/general_misc/vectorish.py
garlicsim_wx/general_misc/wx_tools.py
garlicsim_wx/general_misc/cursor_collection/__init__.py
garlicsim_wx/general_misc/cursor_collection/cursor_collection.py
garlicsim_wx/general_misc/cursor_collection/images/__init__.py
garlicsim_wx/general_misc/cursor_collection/images/closed_grab.png
garlicsim_wx/general_misc/cursor_collection/images/open_grab.png
garlicsim_wx/general_misc/emitters/__init__.py
garlicsim_wx/general_misc/emitters/emitter.py
garlicsim_wx/general_misc/emitters/emitter_system/__init__.py
garlicsim_wx/general_misc/emitters/emitter_system/emitter.py
garlicsim_wx/general_misc/emitters/emitter_system/emitter_system.py
garlicsim_wx/general_misc/third_party/__init__.py
garlicsim_wx/general_misc/third_party/aui/__init__.py
garlicsim_wx/general_misc/third_party/aui/aui_constants.py
garlicsim_wx/general_misc/third_party/aui/aui_switcherdialog.py
garlicsim_wx/general_misc/third_party/aui/aui_utilities.py
