Metadata-Version: 1.1
Name: garlicsim-wx
Version: 0.6.3
Summary: GUI for garlicsim, a Pythonic framework for computer simulations
Home-page: http://garlicsim.org
Author: Ram Rachum
Author-email: cool-rr@cool-rr.com
License: Proprietary
Platform: UNKNOWN
Classifier: Development Status :: 3 - Alpha
Classifier: Intended Audience :: Science/Research
Classifier: Programming Language :: Python
Classifier: Programming Language :: Python :: 2.5
Classifier: Programming Language :: Python :: 2.6
Classifier: Programming Language :: Python :: 2.7
Classifier: Topic :: Scientific/Engineering
Requires: garlicsim (== 0.6.3)
Requires: garlicsim_lib (== 0.6.3)
